{"hourly": [{"hour": 0, "count": 317}, {"hour": 1, "count": 86}, {"hour": 2, "count": 273}, {"hour": 3, "count": 349}, {"hour": 4, "count": 309}, {"hour": 5, "count": 210}, {"hour": 6, "count": 138}, {"hour": 7, "count": 24}, {"hour": 8, "count": 7}, {"hour": 9, "count": 14}, {"hour": 10, "count": 0}, {"hour": 11, "count": 0}, {"hour": 12, "count": 0}, {"hour": 13, "count": 0}, {"hour": 14, "count": 0}, {"hour": 15, "count": 3}, {"hour": 16, "count": 18}, {"hour": 17, "count": 65}, {"hour": 18, "count": 150}, {"hour": 19, "count": 470}, {"hour": 20, "count": 303}, {"hour": 21, "count": 119}, {"hour": 22, "count": 115}, {"hour": 23, "count": 168}], "peak_window": {"start": 2, "end": 5, "count": 931}, "weekday_distribution": [{"day": "Monday", "count": 502}, {"day": "Tuesday", "count": 328}, {"day": "Wednesday", "count": 518}, {"day": "Thursday", "count": 511}, {"day": "Friday", "count": 291}, {"day": "Saturday", "count": 420}, {"day": "Sunday", "count": 568}], "recommendation": "Violations peak between 2:00 AM and 5:00 AM on weekdays. Recommended patrol: deploy by 2:45 AM."}